hemuprogrammes/__init__.py
qwertyuiop/__init__.py
test1/__init__.py
hemuprogrammes-0.1.0.1.8.9.dist-info/LICENCE.txt
hemuprogrammes-0.1.0.1.8.9.dist-info/METADATA
hemuprogrammes-0.1.0.1.8.9.dist-info/WHEEL
hemuprogrammes-0.1.0.1.8.9.dist-info/top_level.txt
hemuprogrammes-0.1.0.1.8.9.dist-info/RECORD
