Metadata-Version: 2.1
Name: hemuprogrammes
Version: 0.1.0.1.8.9
Summary: This is a Combination of GUI and CLI
Author: Hemanth Kumar
Author-email: gujjalahemanthkumar789@gmail.com
Keywords: calculator,PyAutoGUI,pytoexe,Legendary,magic,form,pytoexegui,py to exe,PY TO EXE,autopytoexe,simple GUI calculator,calender without calender module,rock paper scissor game,missing letters game,simple calculator,virtualatm,tkinter
Classifier: Programming Language :: Python :: 3
Classifier: License :: OSI Approved :: MIT License
Classifier: Operating System :: OS Independent
License-File: LICENCE.txt
Requires-Dist: tk
Requires-Dist: pygame
Requires-Dist: mutagen
